dredge/__init__.py
dredge/dredge.py
dredge-1.0.0.dist-info/LICENSE
dredge-1.0.0.dist-info/METADATA
dredge-1.0.0.dist-info/WHEEL
dredge-1.0.0.dist-info/top_level.txt
dredge-1.0.0.dist-info/RECORD
