Metadata-Version: 2.1
Name: dredge
Version: 1.0.0
Summary: User-friendly thresholded subspace-constrained mean shift for geospatial data
Home-page: https://github.com/moews/dredge
Author: Ben Moews
Author-email: ben.moews@protonmail.com
License: UNKNOWN
Keywords: density ridges,spatial analysis,principal curves,route optimization,hot spot analysis
Platform: UNKNOWN
Classifier: Programming Language :: Python :: 3 :: Only
Classifier: Intended Audience :: Science/Research
Classifier: License :: OSI Approved :: MIT License
Requires-Dist: numpy
Requires-Dist: scipy (>=0.18.1)
Requires-Dist: schwimmbad (>=0.3.0)
Requires-Dist: scikit-learn (>=0.19.1)
